{
  "byCourse": [
    {
      "location": "MILANO LEONARDO",
      "sections": [
        "Matematica",
        "Comprensione Verbale",
        "Fisica"
      ],
      "title": "INGEGNERIA CIVILE - CIVIL ENGINEERING",
      "headers": [
        "Posizione",
        "Matricola",
        "Data di Nascita",
        "Immat. consentita",
        "Voto Test",
        "Matematica",
        "Comprensione Verbale",
        "Fisica"
      ],
      "path": "https://www.risultati-ammissione.polimi.it/2024_20056_34cf_html/2024_20056_generale.html",
      "rows": [
        {
          "birthDate": "2005-10-13",
          "englishCorrectAnswers": null,
          "enrollType": {
            "canEnroll": true,
            "course": "INGEGNERIA CIVILE - CIVIL ENGINEERING (MILANO LEONARDO)",
            "type": "Assegnato"
          },
          "id": "d5a06701050cfc2272ff",
          "ofa": {},
          "positionAbsolute": 1,
          "positionCourse": 1,
          "result": 90.00,
          "sectionsResults": {
            "Comprensione Verbale": 15.00,
            "Fisica": 10.00,
            "Matematica": 65.00
          }
        },
        {
          "birthDate": "2005-07-03",
          "englishCorrectAnswers": null,
          "enrollType": {
            "canEnroll": true,
            "course": "INGEGNERIA CIVILE - CIVIL ENGINEERING (MILANO LEONARDO)",
            "type": "Assegnato"
          },
          "id": "f2a8d00dab34b5595382",
          "ofa": {},
          "positionAbsolute": 2,
          "positionCourse": 2,
          "result": 90.00,
          "sectionsResults": {
            "Comprensione Verbale": 15.00,
            "Fisica": 10.00,
            "Matematica": 65.00
          }
        },
        {
          "birthDate": "2003-10-25",
          "englishCorrectAnswers": null,
          "enrollType": {
            "canEnroll": true,
            "course": "INGEGNERIA CIVILE - CIVIL ENGINEERING (MILANO LEONARDO)",
            "type": "Assegnato"
          },
          "id": "13e86599eaee157f6896",
          "ofa": {},
          "positionAbsolute": 3,
          "positionCourse": 3,
          "result": 90.00,
          "sectionsResults": {
            "Comprensione Verbale": 15.00,
            "Fisica": 10.00,
            "Matematica": 65.00
          }
        },
        {
          "birthDate": "2003-10-04",
          "englishCorrectAnswers": null,
          "enrollType": {
            "canEnroll": true,
            "course": "INGEGNERIA CIVILE - CIVIL ENGINEERING (MILANO LEONARDO)",
            "type": "Assegnato"
          },
          "id": "56ef1bc004dc79aa5d7c",
          "ofa": {},
          "positionAbsolute": 4,
          "positionCourse": 4,
          "result": 90.00,
          "sectionsResults": {
            "Comprensione Verbale": 15.00,
            "Fisica": 10.00,
            "Matematica": 65.00
          }
        },
        {
          "birthDate": "2003-08-21",
          "englishCorrectAnswers": null,
          "enrollType": {
            "canEnroll": true,
            "course": "INGEGNERIA CIVILE - CIVIL ENGINEERING (MILANO LEONARDO)",
            "type": "Assegnato"
          },
          "id": "fcf9582d72beb65a0103",
          "ofa": {},
          "positionAbsolute": 5,
          "positionCourse": 5,
          "result": 90.00,
          "sectionsResults": {
            "Comprensione Verbale": 15.00,
            "Fisica": 10.00,
            "Matematica": 65.00
          }
        },
        {
          "birthDate": "2001-12-13",
          "englishCorrectAnswers": null,
          "enrollType": {
            "canEnroll": true,
            "course": "INGEGNERIA CIVILE - CIVIL ENGINEERING (MILANO LEONARDO)",
            "type": "Assegnato"
          },
          "id": "ed9e221e6fc3b75fbbb1",
          "ofa": {},
          "positionAbsolute": 6,
          "positionCourse": 6,
          "result": 90.00,
          "sectionsResults": {
            "Comprensione Verbale": 15.00,
            "Fisica": 10.00,
            "Matematica": 65.00
          }
        },
        {
          "birthDate": "2001-11-01",
          "englishCorrectAnswers": null,
          "enrollType": {
            "canEnroll": true,
            "course": "INGEGNERIA CIVILE - CIVIL ENGINEERING (MILANO LEONARDO)",
            "type": "Assegnato"
          },
          "id": "f933bb190f7e2d5e526e",
          "ofa": {},
          "positionAbsolute": 7,
          "positionCourse": 7,
          "result": 90.00,
          "sectionsResults": {
            "Comprensione Verbale": 15.00,
            "Fisica": 10.00,
            "Matematica": 65.00
          }
        },
        {
          "birthDate": "2005-06-16",
          "englishCorrectAnswers": null,
          "enrollType": {
            "canEnroll": true,
            "course": "INGEGNERIA CIVILE - CIVIL ENGINEERING (MILANO LEONARDO)",
            "type": "Assegnato"
          },
          "id": "c9cfa3ebdfee1fdec248",
          "ofa": {},
          "positionAbsolute": 8,
          "positionCourse": 8,
          "result": 87.89,
          "sectionsResults": {
            "Comprensione Verbale": 15.00,
            "Fisica": 10.00,
            "Matematica": 62.89
          }
        },
        {
          "birthDate": "2006-03-08",
          "englishCorrectAnswers": null,
          "enrollType": {
            "canEnroll": true,
            "course": "INGEGNERIA CIVILE - CIVIL ENGINEERING (MILANO LEONARDO)",
            "type": "Assegnato"
          },
          "id": "7c90738992170861c1fd",
          "ofa": {},
          "positionAbsolute": 9,
          "positionCourse": 9,
          "result": 85.65,
          "sectionsResults": {
            "Comprensione Verbale": 12.76,
            "Fisica": 10.00,
            "Matematica": 62.89
          }
        },
        {
          "birthDate": "2006-09-14",
          "englishCorrectAnswers": null,
          "enrollType": {
            "canEnroll": true,
            "course": "INGEGNERIA CIVILE - CIVIL ENGINEERING (MILANO LEONARDO)",
            "type": "Assegnato"
          },
          "id": "d7b3f92f5c9bad8975be",
          "ofa": {},
          "positionAbsolute": 10,
          "positionCourse": 10,
          "result": 85.40,
          "sectionsResults": {
            "Comprensione Verbale": 15.00,
            "Fisica": 10.00,
            "Matematica": 60.40
          }
        },
        {
          "birthDate": "2006-04-26",
          "englishCorrectAnswers": null,
          "enrollType": {
            "canEnroll": true,
            "course": "INGEGNERIA CIVILE - CIVIL ENGINEERING (MILANO LEONARDO)",
            "type": "Assegnato"
          },
          "id": "e1b779e8818d93bddd3f",
          "ofa": {},
          "positionAbsolute": 11,
          "positionCourse": 11,
          "result": 85.40,
          "sectionsResults": {
            "Comprensione Verbale": 15.00,
            "Fisica": 10.00,
            "Matematica": 60.40
          }
        },
        {
          "birthDate": "2005-11-24",
          "englishCorrectAnswers": null,
          "enrollType": {
            "canEnroll": true,
            "course": "INGEGNERIA CIVILE - CIVIL ENGINEERING (MILANO LEONARDO)",
            "type": "Assegnato"
          },
          "id": "b58916c7d86eb3925803",
          "ofa": {},
          "positionAbsolute": 12,
          "positionCourse": 12,
          "result": 85.40,
          "sectionsResults": {
            "Comprensione Verbale": 15.00,
            "Fisica": 10.00,
            "Matematica": 60.40
          }
        },
        {
          "birthDate": "2005-10-19",
          "englishCorrectAnswers": null,
          "enrollType": {
            "canEnroll": true,
            "course": "INGEGNERIA CIVILE - CIVIL ENGINEERING (MILANO LEONARDO)",
            "type": "Assegnato"
          },
          "id": "dde783954427e78b8589",
          "ofa": {},
          "positionAbsolute": 13,
          "positionCourse": 13,
          "result": 85.40,
          "sectionsResults": {
            "Comprensione Verbale": 15.00,
            "Fisica": 10.00,
            "Matematica": 60.40
          }
        },
        {
          "birthDate": "2005-05-16",
          "englishCorrectAnswers": null,
          "enrollType": {
            "canEnroll": true,
            "course": "INGEGNERIA CIVILE - CIVIL ENGINEERING (MILANO LEONARDO)",
            "type": "Assegnato"
          },
          "id": "957b909607f09a10d5a2",
          "ofa": {},
          "positionAbsolute": 14,
          "positionCourse": 14,
          "result": 85.40,
          "sectionsResults": {
            "Comprensione Verbale": 15.00,
            "Fisica": 10.00,
            "Matematica": 60.40
          }
        },
        {
          "birthDate": "2001-12-13",
          "englishCorrectAnswers": null,
          "enrollType": {
            "canEnroll": true,
            "course": "INGEGNERIA CIVILE - CIVIL ENGINEERING (MILANO LEONARDO)",
            "type": "Assegnato"
          },
          "id": "d5c6650a6e455d7622eb",
          "ofa": {},
          "positionAbsolute": 15,
          "positionCourse": 15,
          "result": 85.40,
          "sectionsResults": {
            "Comprensione Verbale": 15.00,
            "Fisica": 10.00,
            "Matematica": 60.40
          }
        },
        {
          "birthDate": "2001-05-24",
          "englishCorrectAnswers": null,
          "enrollType": {
            "canEnroll": true,
            "course": "INGEGNERIA CIVILE - CIVIL ENGINEERING (MILANO LEONARDO)",
            "type": "Assegnato"
          },
          "id": "09995ffe9855b654f4fc",
          "ofa": {},
          "positionAbsolute": 16,
          "positionCourse": 16,
          "result": 85.40,
          "sectionsResults": {
            "Comprensione Verbale": 15.00,
            "Fisica": 10.00,
            "Matematica": 60.40
          }
        },
        {
          "birthDate": "2000-10-04",
          "englishCorrectAnswers": null,
          "enrollType": {
            "canEnroll": true,
            "course": "INGEGNERIA CIVILE - CIVIL ENGINEERING (MILANO LEONARDO)",
            "type": "Assegnato"
          },
          "id": "36ead16d52584b36942e",
          "ofa": {},
          "positionAbsolute": 17,
          "positionCourse": 17,
          "result": 85.40,
          "sectionsResults": {
            "Comprensione Verbale": 15.00,
            "Fisica": 10.00,
            "Matematica": 60.40
          }
        },
        {
          "birthDate": "2000-02-20",
          "englishCorrectAnswers": null,
          "enrollType": {
            "canEnroll": true,
            "course": "INGEGNERIA CIVILE - CIVIL ENGINEERING (MILANO LEONARDO)",
            "type": "Assegnato"
          },
          "id": "f3367a826ec9e9cddae6",
          "ofa": {},
          "positionAbsolute": 18,
          "positionCourse": 18,
          "result": 85.40,
          "sectionsResults": {
            "Comprensione Verbale": 15.00,
            "Fisica": 10.00,
            "Matematica": 60.40
          }
        },
        {
          "birthDate": "2006-07-08",
          "englishCorrectAnswers": null,
          "enrollType": {
            "canEnroll": true,
            "course": "INGEGNERIA CIVILE - CIVIL ENGINEERING (MILANO LEONARDO)",
            "type": "Assegnato"
          },
          "id": "9c4cbb1b5fb6ba4d5e4b",
          "ofa": {},
          "positionAbsolute": 19,
          "positionCourse": 19,
          "result": 83.47,
          "sectionsResults": {
            "Comprensione Verbale": 15.00,
            "Fisica": 8.07,
            "Matematica": 60.40
          }
        },
        {
          "birthDate": "2003-10-01",
          "englishCorrectAnswers": null,
          "enrollType": {
            "canEnroll": true,
            "course": "INGEGNERIA CIVILE - CIVIL ENGINEERING (MILANO LEONARDO)",
            "type": "Assegnato"
          },
          "id": "22d1f427f44f5e818b7a",
          "ofa": {},
          "positionAbsolute": 20,
          "positionCourse": 20,
          "result": 83.29,
          "sectionsResults": {
            "Comprensione Verbale": 15.00,
            "Fisica": 10.00,
            "Matematica": 58.29
          }
        },
        {
          "birthDate": "2006-02-03",
          "englishCorrectAnswers": null,
          "enrollType": {
            "canEnroll": true,
            "course": "INGEGNERIA CIVILE - CIVIL ENGINEERING (MILANO LEONARDO)",
            "type": "Assegnato"
          },
          "id": "ed80181cd05c42990328",
          "ofa": {},
          "positionAbsolute": 21,
          "positionCourse": 21,
          "result": 81.18,
          "sectionsResults": {
            "Comprensione Verbale": 15.00,
            "Fisica": 10.00,
            "Matematica": 56.18
          }
        },
        {
          "birthDate": "2002-02-12",
          "englishCorrectAnswers": null,
          "enrollType": {
            "canEnroll": true,
            "course": "INGEGNERIA CIVILE - CIVIL ENGINEERING (MILANO LEONARDO)",
            "type": "Assegnato"
          },
          "id": "b25b4e5181007f413724",
          "ofa": {},
          "positionAbsolute": 22,
          "positionCourse": 22,
          "result": 80.79,
          "sectionsResults": {
            "Comprensione Verbale": 15.00,
            "Fisica": 10.00,
            "Matematica": 55.79
          }
        },
        {
          "birthDate": "2003-03-05",
          "englishCorrectAnswers": null,
          "enrollType": {
            "canEnroll": true,
            "course": "INGEGNERIA CIVILE - CIVIL ENGINEERING (MILANO LEONARDO)",
            "type": "Assegnato"
          },
          "id": "7810319c3d3ddf5f7904",
          "ofa": {},
          "positionAbsolute": 23,
          "positionCourse": 23,
          "result": 79.00,
          "sectionsResults": {
            "Comprensione Verbale": 10.53,
            "Fisica": 8.07,
            "Matematica": 60.40
          }
        },
        {
          "birthDate": "2002-04-07",
          "englishCorrectAnswers": null,
          "enrollType": {
            "canEnroll": true,
            "course": "INGEGNERIA CIVILE - CIVIL ENGINEERING (MILANO LEONARDO)",
            "type": "Assegnato"
          },
          "id": "08aa4353c952ab45c246",
          "ofa": {},
          "positionAbsolute": 24,
          "positionCourse": 24,
          "result": 78.86,
          "sectionsResults": {
            "Comprensione Verbale": 15.00,
            "Fisica": 8.07,
            "Matematica": 55.79
          }
        },
        {
          "birthDate": "2005-06-13",
          "englishCorrectAnswers": null,
          "enrollType": {
            "canEnroll": true,
            "course": "INGEGNERIA CIVILE - CIVIL ENGINEERING (MILANO LEONARDO)",
            "type": "Assegnato"
          },
          "id": "d94acaa044dfc990360d",
          "ofa": {},
          "positionAbsolute": 25,
          "positionCourse": 25,
          "result": 78.82,
          "sectionsResults": {
            "Comprensione Verbale": 10.53,
            "Fisica": 10.00,
            "Matematica": 58.29
          }
        },
        {
          "birthDate": "2003-07-12",
          "englishCorrectAnswers": null,
          "enrollType": {
            "canEnroll": true,
            "course": "INGEGNERIA CIVILE - CIVIL ENGINEERING (MILANO LEONARDO)",
            "type": "Assegnato"
          },
          "id": "542653b7f41eca8b9824",
          "ofa": {},
          "positionAbsolute": 26,
          "positionCourse": 26,
          "result": 76.92,
          "sectionsResults": {
            "Comprensione Verbale": 15.00,
            "Fisica": 6.13,
            "Matematica": 55.79
          }
        },
        {
          "birthDate": "2001-02-13",
          "englishCorrectAnswers": null,
          "enrollType": {
            "canEnroll": true,
            "course": "INGEGNERIA CIVILE - CIVIL ENGINEERING (MILANO LEONARDO)",
            "type": "Assegnato"
          },
          "id": "b5735242113fcc64284e",
          "ofa": {},
          "positionAbsolute": 27,
          "positionCourse": 27,
          "result": 72.57,
          "sectionsResults": {
            "Comprensione Verbale": 12.76,
            "Fisica": 6.13,
            "Matematica": 53.68
          }
        },
        {
          "birthDate": "2005-03-19",
          "englishCorrectAnswers": null,
          "enrollType": {
            "canEnroll": true,
            "course": "INGEGNERIA CIVILE - CIVIL ENGINEERING (MILANO LEONARDO)",
            "type": "Assegnato"
          },
          "id": "a4f9b40b05725c9ce89b",
          "ofa": {},
          "positionAbsolute": 28,
          "positionCourse": 28,
          "result": 72.29,
          "sectionsResults": {
            "Comprensione Verbale": 10.53,
            "Fisica": 3.47,
            "Matematica": 58.29
          }
        },
        {
          "birthDate": "2004-09-23",
          "englishCorrectAnswers": null,
          "enrollType": {
            "canEnroll": true,
            "course": "INGEGNERIA CIVILE - CIVIL ENGINEERING (MILANO LEONARDO)",
            "type": "Assegnato"
          },
          "id": "c0aa605c044666402127",
          "ofa": {},
          "positionAbsolute": 29,
          "positionCourse": 29,
          "result": 72.16,
          "sectionsResults": {
            "Comprensione Verbale": 3.31,
            "Fisica": 8.07,
            "Matematica": 60.78
          }
        },
        {
          "birthDate": "2001-09-14",
          "englishCorrectAnswers": null,
          "enrollType": {
            "canEnroll": true,
            "course": "INGEGNERIA CIVILE - CIVIL ENGINEERING (MILANO LEONARDO)",
            "type": "Assegnato"
          },
          "id": "c75a6d0f6143a4c001bc",
          "ofa": {},
          "positionAbsolute": 30,
          "positionCourse": 30,
          "result": 71.69,
          "sectionsResults": {
            "Comprensione Verbale": 15.00,
            "Fisica": 4.58,
            "Matematica": 52.11
          }
        },
        {
          "birthDate": "2006-01-26",
          "englishCorrectAnswers": null,
          "enrollType": {
            "canEnroll": true,
            "course": "INGEGNERIA CIVILE - CIVIL ENGINEERING (MILANO LEONARDO)",
            "type": "Assegnato"
          },
          "id": "c23c4b8a8979a7aa34d8",
          "ofa": {},
          "positionAbsolute": 31,
          "positionCourse": 31,
          "result": 64.58,
          "sectionsResults": {
            "Comprensione Verbale": 12.76,
            "Fisica": 6.90,
            "Matematica": 44.92
          }
        },
        {
          "birthDate": "2005-02-25",
          "englishCorrectAnswers": null,
          "enrollType": {
            "canEnroll": true,
            "course": "INGEGNERIA CIVILE - CIVIL ENGINEERING (MILANO LEONARDO)",
            "type": "Assegnato"
          },
          "id": "8516c53e37ca06817ca3",
          "ofa": {},
          "positionAbsolute": 32,
          "positionCourse": 32,
          "result": 59.48,
          "sectionsResults": {
            "Comprensione Verbale": 6.94,
            "Fisica": 8.07,
            "Matematica": 44.47
          }
        },
        {
          "birthDate": "2003-05-12",
          "englishCorrectAnswers": null,
          "enrollType": {
            "canEnroll": true,
            "course": "INGEGNERIA CIVILE - CIVIL ENGINEERING (MILANO LEONARDO)",
            "type": "Assegnato"
          },
          "id": "97b17a1246c5e6d91d26",
          "ofa": {},
          "positionAbsolute": 33,
          "positionCourse": 33,
          "result": 55.03,
          "sectionsResults": {
            "Comprensione Verbale": 12.76,
            "Fisica": 1.06,
            "Matematica": 41.21
          }
        },
        {
          "birthDate": "2005-09-04",
          "englishCorrectAnswers": null,
          "enrollType": {
            "canEnroll": true,
            "course": "INGEGNERIA CIVILE - CIVIL ENGINEERING (MILANO LEONARDO)",
            "type": "Assegnato"
          },
          "id": "7f110c8c5c1456a07f8d",
          "ofa": {},
          "positionAbsolute": 34,
          "positionCourse": 34,
          "result": 50.03,
          "sectionsResults": {
            "Comprensione Verbale": 12.76,
            "Fisica": 4.58,
            "Matematica": 32.69
          }
        },
        {
          "birthDate": "2004-03-15",
          "englishCorrectAnswers": null,
          "enrollType": {
            "canEnroll": true,
            "course": "INGEGNERIA CIVILE - CIVIL ENGINEERING (MILANO LEONARDO)",
            "type": "Assegnato"
          },
          "id": "9e61e57ac15f12a03a98",
          "ofa": {},
          "positionAbsolute": 35,
          "positionCourse": 35,
          "result": 49.91,
          "sectionsResults": {
            "Comprensione Verbale": 10.53,
            "Fisica": 4.20,
            "Matematica": 35.18
          }
        },
        {
          "birthDate": "2006-06-30",
          "englishCorrectAnswers": null,
          "enrollType": {
            "canEnroll": true,
            "course": "INGEGNERIA CIVILE - CIVIL ENGINEERING (MILANO LEONARDO)",
            "type": "Assegnato"
          },
          "id": "3169df6d7037d5675749",
          "ofa": {},
          "positionAbsolute": 36,
          "positionCourse": 36,
          "result": 49.28,
          "sectionsResults": {
            "Comprensione Verbale": 12.76,
            "Fisica": 2.26,
            "Matematica": 34.26
          }
        },
        {
          "birthDate": "2005-08-08",
          "englishCorrectAnswers": null,
          "enrollType": {
            "canEnroll": false,
            "course": null,
            "type": null
          },
          "id": "cd92435e314fa19c40d0",
          "ofa": {},
          "positionAbsolute": 37,
          "positionCourse": 37,
          "result": 48.08,
          "sectionsResults": {
            "Comprensione Verbale": 12.76,
            "Fisica": 4.20,
            "Matematica": 31.12
          }
        },
        {
          "birthDate": "2005-03-14",
          "englishCorrectAnswers": null,
          "enrollType": {
            "canEnroll": false,
            "course": null,
            "type": null
          },
          "id": "2a8e041e72ca35c5b984",
          "ofa": {},
          "positionAbsolute": 38,
          "positionCourse": 38,
          "result": 42.13,
          "sectionsResults": {
            "Comprensione Verbale": 5.95,
            "Fisica": 3.17,
            "Matematica": 33.01
          }
        },
        {
          "birthDate": "2005-09-19",
          "englishCorrectAnswers": null,
          "enrollType": {
            "canEnroll": false,
            "course": null,
            "type": null
          },
          "id": "171ede8aa5602ba7c70c",
          "ofa": {},
          "positionAbsolute": 39,
          "positionCourse": 39,
          "result": 42.12,
          "sectionsResults": {
            "Comprensione Verbale": 6.61,
            "Fisica": 2.41,
            "Matematica": 33.10
          }
        },
        {
          "birthDate": "2005-01-01",
          "englishCorrectAnswers": null,
          "enrollType": {
            "canEnroll": false,
            "course": null,
            "type": null
          },
          "id": "0bff84f2329ba3ab9011",
          "ofa": {},
          "positionAbsolute": 40,
          "positionCourse": 40,
          "result": 33.32,
          "sectionsResults": {
            "Comprensione Verbale": 2.31,
            "Fisica": 3.17,
            "Matematica": 27.84
          }
        },
        {
          "birthDate": "2006-10-16",
          "englishCorrectAnswers": null,
          "enrollType": {
            "canEnroll": false,
            "course": null,
            "type": null
          },
          "id": "227e6cee14fc5cdb9d36",
          "ofa": {},
          "positionAbsolute": 41,
          "positionCourse": 41,
          "result": 30.31,
          "sectionsResults": {
            "Comprensione Verbale": 8.74,
            "Fisica": -0.15,
            "Matematica": 21.72
          }
        }
      ],
      "year": 2024
    }
  ],
  "byMerit": {
    "headers": [
      "Matricola",
      "Voto Test",
      "Posizione Assoluta",
      "Corso di Studi per il quale è consentita l'immatricolazione"
    ],
    "path": "https://www.risultati-ammissione.polimi.it/2024_20056_34cf_html/2024_20056_generale.html",
    "rows": [
      {
        "birthDate": "2005-10-13",
        "englishCorrectAnswers": null,
        "enrollType": {
          "canEnroll": true,
          "course": "INGEGNERIA CIVILE - CIVIL ENGINEERING (MILANO LEONARDO)",
          "type": "Assegnato"
        },
        "id": "d5a06701050cfc2272ff",
        "ofa": {},
        "positionAbsolute": 1,
        "positionCourse": 1,
        "result": 90.00,
        "sectionsResults": {
          "Comprensione Verbale": 15.00,
          "Fisica": 10.00,
          "Matematica": 65.00
        }
      },
      {
        "birthDate": "2005-07-03",
        "englishCorrectAnswers": null,
        "enrollType": {
          "canEnroll": true,
          "course": "INGEGNERIA CIVILE - CIVIL ENGINEERING (MILANO LEONARDO)",
          "type": "Assegnato"
        },
        "id": "f2a8d00dab34b5595382",
        "ofa": {},
        "positionAbsolute": 2,
        "positionCourse": 2,
        "result": 90.00,
        "sectionsResults": {
          "Comprensione Verbale": 15.00,
          "Fisica": 10.00,
          "Matematica": 65.00
        }
      },
      {
        "birthDate": "2003-10-25",
        "englishCorrectAnswers": null,
        "enrollType": {
          "canEnroll": true,
          "course": "INGEGNERIA CIVILE - CIVIL ENGINEERING (MILANO LEONARDO)",
          "type": "Assegnato"
        },
        "id": "13e86599eaee157f6896",
        "ofa": {},
        "positionAbsolute": 3,
        "positionCourse": 3,
        "result": 90.00,
        "sectionsResults": {
          "Comprensione Verbale": 15.00,
          "Fisica": 10.00,
          "Matematica": 65.00
        }
      },
      {
        "birthDate": "2003-10-04",
        "englishCorrectAnswers": null,
        "enrollType": {
          "canEnroll": true,
          "course": "INGEGNERIA CIVILE - CIVIL ENGINEERING (MILANO LEONARDO)",
          "type": "Assegnato"
        },
        "id": "56ef1bc004dc79aa5d7c",
        "ofa": {},
        "positionAbsolute": 4,
        "positionCourse": 4,
        "result": 90.00,
        "sectionsResults": {
          "Comprensione Verbale": 15.00,
          "Fisica": 10.00,
          "Matematica": 65.00
        }
      },
      {
        "birthDate": "2003-08-21",
        "englishCorrectAnswers": null,
        "enrollType": {
          "canEnroll": true,
          "course": "INGEGNERIA CIVILE - CIVIL ENGINEERING (MILANO LEONARDO)",
          "type": "Assegnato"
        },
        "id": "fcf9582d72beb65a0103",
        "ofa": {},
        "positionAbsolute": 5,
        "positionCourse": 5,
        "result": 90.00,
        "sectionsResults": {
          "Comprensione Verbale": 15.00,
          "Fisica": 10.00,
          "Matematica": 65.00
        }
      },
      {
        "birthDate": "2001-12-13",
        "englishCorrectAnswers": null,
        "enrollType": {
          "canEnroll": true,
          "course": "INGEGNERIA CIVILE - CIVIL ENGINEERING (MILANO LEONARDO)",
          "type": "Assegnato"
        },
        "id": "ed9e221e6fc3b75fbbb1",
        "ofa": {},
        "positionAbsolute": 6,
        "positionCourse": 6,
        "result": 90.00,
        "sectionsResults": {
          "Comprensione Verbale": 15.00,
          "Fisica": 10.00,
          "Matematica": 65.00
        }
      },
      {
        "birthDate": "2001-11-01",
        "englishCorrectAnswers": null,
        "enrollType": {
          "canEnroll": true,
          "course": "INGEGNERIA CIVILE - CIVIL ENGINEERING (MILANO LEONARDO)",
          "type": "Assegnato"
        },
        "id": "f933bb190f7e2d5e526e",
        "ofa": {},
        "positionAbsolute": 7,
        "positionCourse": 7,
        "result": 90.00,
        "sectionsResults": {
          "Comprensione Verbale": 15.00,
          "Fisica": 10.00,
          "Matematica": 65.00
        }
      },
      {
        "birthDate": "2005-06-16",
        "englishCorrectAnswers": null,
        "enrollType": {
          "canEnroll": true,
          "course": "INGEGNERIA CIVILE - CIVIL ENGINEERING (MILANO LEONARDO)",
          "type": "Assegnato"
        },
        "id": "c9cfa3ebdfee1fdec248",
        "ofa": {},
        "positionAbsolute": 8,
        "positionCourse": 8,
        "result": 87.89,
        "sectionsResults": {
          "Comprensione Verbale": 15.00,
          "Fisica": 10.00,
          "Matematica": 62.89
        }
      },
      {
        "birthDate": "2006-03-08",
        "englishCorrectAnswers": null,
        "enrollType": {
          "canEnroll": true,
          "course": "INGEGNERIA CIVILE - CIVIL ENGINEERING (MILANO LEONARDO)",
          "type": "Assegnato"
        },
        "id": "7c90738992170861c1fd",
        "ofa": {},
        "positionAbsolute": 9,
        "positionCourse": 9,
        "result": 85.65,
        "sectionsResults": {
          "Comprensione Verbale": 12.76,
          "Fisica": 10.00,
          "Matematica": 62.89
        }
      },
      {
        "birthDate": "2006-09-14",
        "englishCorrectAnswers": null,
        "enrollType": {
          "canEnroll": true,
          "course": "INGEGNERIA CIVILE - CIVIL ENGINEERING (MILANO LEONARDO)",
          "type": "Assegnato"
        },
        "id": "d7b3f92f5c9bad8975be",
        "ofa": {},
        "positionAbsolute": 10,
        "positionCourse": 10,
        "result": 85.40,
        "sectionsResults": {
          "Comprensione Verbale": 15.00,
          "Fisica": 10.00,
          "Matematica": 60.40
        }
      },
      {
        "birthDate": "2006-04-26",
        "englishCorrectAnswers": null,
        "enrollType": {
          "canEnroll": true,
          "course": "INGEGNERIA CIVILE - CIVIL ENGINEERING (MILANO LEONARDO)",
          "type": "Assegnato"
        },
        "id": "e1b779e8818d93bddd3f",
        "ofa": {},
        "positionAbsolute": 11,
        "positionCourse": 11,
        "result": 85.40,
        "sectionsResults": {
          "Comprensione Verbale": 15.00,
          "Fisica": 10.00,
          "Matematica": 60.40
        }
      },
      {
        "birthDate": "2005-11-24",
        "englishCorrectAnswers": null,
        "enrollType": {
          "canEnroll": true,
          "course": "INGEGNERIA CIVILE - CIVIL ENGINEERING (MILANO LEONARDO)",
          "type": "Assegnato"
        },
        "id": "b58916c7d86eb3925803",
        "ofa": {},
        "positionAbsolute": 12,
        "positionCourse": 12,
        "result": 85.40,
        "sectionsResults": {
          "Comprensione Verbale": 15.00,
          "Fisica": 10.00,
          "Matematica": 60.40
        }
      },
      {
        "birthDate": "2005-10-19",
        "englishCorrectAnswers": null,
        "enrollType": {
          "canEnroll": true,
          "course": "INGEGNERIA CIVILE - CIVIL ENGINEERING (MILANO LEONARDO)",
          "type": "Assegnato"
        },
        "id": "dde783954427e78b8589",
        "ofa": {},
        "positionAbsolute": 13,
        "positionCourse": 13,
        "result": 85.40,
        "sectionsResults": {
          "Comprensione Verbale": 15.00,
          "Fisica": 10.00,
          "Matematica": 60.40
        }
      },
      {
        "birthDate": "2005-05-16",
        "englishCorrectAnswers": null,
        "enrollType": {
          "canEnroll": true,
          "course": "INGEGNERIA CIVILE - CIVIL ENGINEERING (MILANO LEONARDO)",
          "type": "Assegnato"
        },
        "id": "957b909607f09a10d5a2",
        "ofa": {},
        "positionAbsolute": 14,
        "positionCourse": 14,
        "result": 85.40,
        "sectionsResults": {
          "Comprensione Verbale": 15.00,
          "Fisica": 10.00,
          "Matematica": 60.40
        }
      },
      {
        "birthDate": "2001-12-13",
        "englishCorrectAnswers": null,
        "enrollType": {
          "canEnroll": true,
          "course": "INGEGNERIA CIVILE - CIVIL ENGINEERING (MILANO LEONARDO)",
          "type": "Assegnato"
        },
        "id": "d5c6650a6e455d7622eb",
        "ofa": {},
        "positionAbsolute": 15,
        "positionCourse": 15,
        "result": 85.40,
        "sectionsResults": {
          "Comprensione Verbale": 15.00,
          "Fisica": 10.00,
          "Matematica": 60.40
        }
      },
      {
        "birthDate": "2001-05-24",
        "englishCorrectAnswers": null,
        "enrollType": {
          "canEnroll": true,
          "course": "INGEGNERIA CIVILE - CIVIL ENGINEERING (MILANO LEONARDO)",
          "type": "Assegnato"
        },
        "id": "09995ffe9855b654f4fc",
        "ofa": {},
        "positionAbsolute": 16,
        "positionCourse": 16,
        "result": 85.40,
        "sectionsResults": {
          "Comprensione Verbale": 15.00,
          "Fisica": 10.00,
          "Matematica": 60.40
        }
      },
      {
        "birthDate": "2000-10-04",
        "englishCorrectAnswers": null,
        "enrollType": {
          "canEnroll": true,
          "course": "INGEGNERIA CIVILE - CIVIL ENGINEERING (MILANO LEONARDO)",
          "type": "Assegnato"
        },
        "id": "36ead16d52584b36942e",
        "ofa": {},
        "positionAbsolute": 17,
        "positionCourse": 17,
        "result": 85.40,
        "sectionsResults": {
          "Comprensione Verbale": 15.00,
          "Fisica": 10.00,
          "Matematica": 60.40
        }
      },
      {
        "birthDate": "2000-02-20",
        "englishCorrectAnswers": null,
        "enrollType": {
          "canEnroll": true,
          "course": "INGEGNERIA CIVILE - CIVIL ENGINEERING (MILANO LEONARDO)",
          "type": "Assegnato"
        },
        "id": "f3367a826ec9e9cddae6",
        "ofa": {},
        "positionAbsolute": 18,
        "positionCourse": 18,
        "result": 85.40,
        "sectionsResults": {
          "Comprensione Verbale": 15.00,
          "Fisica": 10.00,
          "Matematica": 60.40
        }
      },
      {
        "birthDate": "2006-07-08",
        "englishCorrectAnswers": null,
        "enrollType": {
          "canEnroll": true,
          "course": "INGEGNERIA CIVILE - CIVIL ENGINEERING (MILANO LEONARDO)",
          "type": "Assegnato"
        },
        "id": "9c4cbb1b5fb6ba4d5e4b",
        "ofa": {},
        "positionAbsolute": 19,
        "positionCourse": 19,
        "result": 83.47,
        "sectionsResults": {
          "Comprensione Verbale": 15.00,
          "Fisica": 8.07,
          "Matematica": 60.40
        }
      },
      {
        "birthDate": "2003-10-01",
        "englishCorrectAnswers": null,
        "enrollType": {
          "canEnroll": true,
          "course": "INGEGNERIA CIVILE - CIVIL ENGINEERING (MILANO LEONARDO)",
          "type": "Assegnato"
        },
        "id": "22d1f427f44f5e818b7a",
        "ofa": {},
        "positionAbsolute": 20,
        "positionCourse": 20,
        "result": 83.29,
        "sectionsResults": {
          "Comprensione Verbale": 15.00,
          "Fisica": 10.00,
          "Matematica": 58.29
        }
      },
      {
        "birthDate": "2006-02-03",
        "englishCorrectAnswers": null,
        "enrollType": {
          "canEnroll": true,
          "course": "INGEGNERIA CIVILE - CIVIL ENGINEERING (MILANO LEONARDO)",
          "type": "Assegnato"
        },
        "id": "ed80181cd05c42990328",
        "ofa": {},
        "positionAbsolute": 21,
        "positionCourse": 21,
        "result": 81.18,
        "sectionsResults": {
          "Comprensione Verbale": 15.00,
          "Fisica": 10.00,
          "Matematica": 56.18
        }
      },
      {
        "birthDate": "2002-02-12",
        "englishCorrectAnswers": null,
        "enrollType": {
          "canEnroll": true,
          "course": "INGEGNERIA CIVILE - CIVIL ENGINEERING (MILANO LEONARDO)",
          "type": "Assegnato"
        },
        "id": "b25b4e5181007f413724",
        "ofa": {},
        "positionAbsolute": 22,
        "positionCourse": 22,
        "result": 80.79,
        "sectionsResults": {
          "Comprensione Verbale": 15.00,
          "Fisica": 10.00,
          "Matematica": 55.79
        }
      },
      {
        "birthDate": "2003-03-05",
        "englishCorrectAnswers": null,
        "enrollType": {
          "canEnroll": true,
          "course": "INGEGNERIA CIVILE - CIVIL ENGINEERING (MILANO LEONARDO)",
          "type": "Assegnato"
        },
        "id": "7810319c3d3ddf5f7904",
        "ofa": {},
        "positionAbsolute": 23,
        "positionCourse": 23,
        "result": 79.00,
        "sectionsResults": {
          "Comprensione Verbale": 10.53,
          "Fisica": 8.07,
          "Matematica": 60.40
        }
      },
      {
        "birthDate": "2002-04-07",
        "englishCorrectAnswers": null,
        "enrollType": {
          "canEnroll": true,
          "course": "INGEGNERIA CIVILE - CIVIL ENGINEERING (MILANO LEONARDO)",
          "type": "Assegnato"
        },
        "id": "08aa4353c952ab45c246",
        "ofa": {},
        "positionAbsolute": 24,
        "positionCourse": 24,
        "result": 78.86,
        "sectionsResults": {
          "Comprensione Verbale": 15.00,
          "Fisica": 8.07,
          "Matematica": 55.79
        }
      },
      {
        "birthDate": "2005-06-13",
        "englishCorrectAnswers": null,
        "enrollType": {
          "canEnroll": true,
          "course": "INGEGNERIA CIVILE - CIVIL ENGINEERING (MILANO LEONARDO)",
          "type": "Assegnato"
        },
        "id": "d94acaa044dfc990360d",
        "ofa": {},
        "positionAbsolute": 25,
        "positionCourse": 25,
        "result": 78.82,
        "sectionsResults": {
          "Comprensione Verbale": 10.53,
          "Fisica": 10.00,
          "Matematica": 58.29
        }
      },
      {
        "birthDate": "2003-07-12",
        "englishCorrectAnswers": null,
        "enrollType": {
          "canEnroll": true,
          "course": "INGEGNERIA CIVILE - CIVIL ENGINEERING (MILANO LEONARDO)",
          "type": "Assegnato"
        },
        "id": "542653b7f41eca8b9824",
        "ofa": {},
        "positionAbsolute": 26,
        "positionCourse": 26,
        "result": 76.92,
        "sectionsResults": {
          "Comprensione Verbale": 15.00,
          "Fisica": 6.13,
          "Matematica": 55.79
        }
      },
      {
        "birthDate": "2001-02-13",
        "englishCorrectAnswers": null,
        "enrollType": {
          "canEnroll": true,
          "course": "INGEGNERIA CIVILE - CIVIL ENGINEERING (MILANO LEONARDO)",
          "type": "Assegnato"
        },
        "id": "b5735242113fcc64284e",
        "ofa": {},
        "positionAbsolute": 27,
        "positionCourse": 27,
        "result": 72.57,
        "sectionsResults": {
          "Comprensione Verbale": 12.76,
          "Fisica": 6.13,
          "Matematica": 53.68
        }
      },
      {
        "birthDate": "2005-03-19",
        "englishCorrectAnswers": null,
        "enrollType": {
          "canEnroll": true,
          "course": "INGEGNERIA CIVILE - CIVIL ENGINEERING (MILANO LEONARDO)",
          "type": "Assegnato"
        },
        "id": "a4f9b40b05725c9ce89b",
        "ofa": {},
        "positionAbsolute": 28,
        "positionCourse": 28,
        "result": 72.29,
        "sectionsResults": {
          "Comprensione Verbale": 10.53,
          "Fisica": 3.47,
          "Matematica": 58.29
        }
      },
      {
        "birthDate": "2004-09-23",
        "englishCorrectAnswers": null,
        "enrollType": {
          "canEnroll": true,
          "course": "INGEGNERIA CIVILE - CIVIL ENGINEERING (MILANO LEONARDO)",
          "type": "Assegnato"
        },
        "id": "c0aa605c044666402127",
        "ofa": {},
        "positionAbsolute": 29,
        "positionCourse": 29,
        "result": 72.16,
        "sectionsResults": {
          "Comprensione Verbale": 3.31,
          "Fisica": 8.07,
          "Matematica": 60.78
        }
      },
      {
        "birthDate": "2001-09-14",
        "englishCorrectAnswers": null,
        "enrollType": {
          "canEnroll": true,
          "course": "INGEGNERIA CIVILE - CIVIL ENGINEERING (MILANO LEONARDO)",
          "type": "Assegnato"
        },
        "id": "c75a6d0f6143a4c001bc",
        "ofa": {},
        "positionAbsolute": 30,
        "positionCourse": 30,
        "result": 71.69,
        "sectionsResults": {
          "Comprensione Verbale": 15.00,
          "Fisica": 4.58,
          "Matematica": 52.11
        }
      },
      {
        "birthDate": "2006-01-26",
        "englishCorrectAnswers": null,
        "enrollType": {
          "canEnroll": true,
          "course": "INGEGNERIA CIVILE - CIVIL ENGINEERING (MILANO LEONARDO)",
          "type": "Assegnato"
        },
        "id": "c23c4b8a8979a7aa34d8",
        "ofa": {},
        "positionAbsolute": 31,
        "positionCourse": 31,
        "result": 64.58,
        "sectionsResults": {
          "Comprensione Verbale": 12.76,
          "Fisica": 6.90,
          "Matematica": 44.92
        }
      },
      {
        "birthDate": "2005-02-25",
        "englishCorrectAnswers": null,
        "enrollType": {
          "canEnroll": true,
          "course": "INGEGNERIA CIVILE - CIVIL ENGINEERING (MILANO LEONARDO)",
          "type": "Assegnato"
        },
        "id": "8516c53e37ca06817ca3",
        "ofa": {},
        "positionAbsolute": 32,
        "positionCourse": 32,
        "result": 59.48,
        "sectionsResults": {
          "Comprensione Verbale": 6.94,
          "Fisica": 8.07,
          "Matematica": 44.47
        }
      },
      {
        "birthDate": "2003-05-12",
        "englishCorrectAnswers": null,
        "enrollType": {
          "canEnroll": true,
          "course": "INGEGNERIA CIVILE - CIVIL ENGINEERING (MILANO LEONARDO)",
          "type": "Assegnato"
        },
        "id": "97b17a1246c5e6d91d26",
        "ofa": {},
        "positionAbsolute": 33,
        "positionCourse": 33,
        "result": 55.03,
        "sectionsResults": {
          "Comprensione Verbale": 12.76,
          "Fisica": 1.06,
          "Matematica": 41.21
        }
      },
      {
        "birthDate": "2005-09-04",
        "englishCorrectAnswers": null,
        "enrollType": {
          "canEnroll": true,
          "course": "INGEGNERIA CIVILE - CIVIL ENGINEERING (MILANO LEONARDO)",
          "type": "Assegnato"
        },
        "id": "7f110c8c5c1456a07f8d",
        "ofa": {},
        "positionAbsolute": 34,
        "positionCourse": 34,
        "result": 50.03,
        "sectionsResults": {
          "Comprensione Verbale": 12.76,
          "Fisica": 4.58,
          "Matematica": 32.69
        }
      },
      {
        "birthDate": "2004-03-15",
        "englishCorrectAnswers": null,
        "enrollType": {
          "canEnroll": true,
          "course": "INGEGNERIA CIVILE - CIVIL ENGINEERING (MILANO LEONARDO)",
          "type": "Assegnato"
        },
        "id": "9e61e57ac15f12a03a98",
        "ofa": {},
        "positionAbsolute": 35,
        "positionCourse": 35,
        "result": 49.91,
        "sectionsResults": {
          "Comprensione Verbale": 10.53,
          "Fisica": 4.20,
          "Matematica": 35.18
        }
      },
      {
        "birthDate": "2006-06-30",
        "englishCorrectAnswers": null,
        "enrollType": {
          "canEnroll": true,
          "course": "INGEGNERIA CIVILE - CIVIL ENGINEERING (MILANO LEONARDO)",
          "type": "Assegnato"
        },
        "id": "3169df6d7037d5675749",
        "ofa": {},
        "positionAbsolute": 36,
        "positionCourse": 36,
        "result": 49.28,
        "sectionsResults": {
          "Comprensione Verbale": 12.76,
          "Fisica": 2.26,
          "Matematica": 34.26
        }
      },
      {
        "birthDate": "2005-08-08",
        "englishCorrectAnswers": null,
        "enrollType": {
          "canEnroll": false,
          "course": null,
          "type": null
        },
        "id": "cd92435e314fa19c40d0",
        "ofa": {},
        "positionAbsolute": 37,
        "positionCourse": 37,
        "result": 48.08,
        "sectionsResults": {
          "Comprensione Verbale": 12.76,
          "Fisica": 4.20,
          "Matematica": 31.12
        }
      },
      {
        "birthDate": "2005-03-14",
        "englishCorrectAnswers": null,
        "enrollType": {
          "canEnroll": false,
          "course": null,
          "type": null
        },
        "id": "2a8e041e72ca35c5b984",
        "ofa": {},
        "positionAbsolute": 38,
        "positionCourse": 38,
        "result": 42.13,
        "sectionsResults": {
          "Comprensione Verbale": 5.95,
          "Fisica": 3.17,
          "Matematica": 33.01
        }
      },
      {
        "birthDate": "2005-09-19",
        "englishCorrectAnswers": null,
        "enrollType": {
          "canEnroll": false,
          "course": null,
          "type": null
        },
        "id": "171ede8aa5602ba7c70c",
        "ofa": {},
        "positionAbsolute": 39,
        "positionCourse": 39,
        "result": 42.12,
        "sectionsResults": {
          "Comprensione Verbale": 6.61,
          "Fisica": 2.41,
          "Matematica": 33.10
        }
      },
      {
        "birthDate": "2005-01-01",
        "englishCorrectAnswers": null,
        "enrollType": {
          "canEnroll": false,
          "course": null,
          "type": null
        },
        "id": "0bff84f2329ba3ab9011",
        "ofa": {},
        "positionAbsolute": 40,
        "positionCourse": 40,
        "result": 33.32,
        "sectionsResults": {
          "Comprensione Verbale": 2.31,
          "Fisica": 3.17,
          "Matematica": 27.84
        }
      },
      {
        "birthDate": "2006-10-16",
        "englishCorrectAnswers": null,
        "enrollType": {
          "canEnroll": false,
          "course": null,
          "type": null
        },
        "id": "227e6cee14fc5cdb9d36",
        "ofa": {},
        "positionAbsolute": 41,
        "positionCourse": 41,
        "result": 30.31,
        "sectionsResults": {
          "Comprensione Verbale": 8.74,
          "Fisica": -0.15,
          "Matematica": 21.72
        }
      }
    ],
    "year": 2024
  },
  "extra": "Studenti Extra-UE: Contingente riservato incluso Contingente 'Marco Polo'",
  "lastUpdate": "2024-07-04T13:08:38.001944Z",
  "rankingOrder": {
    "anticipata": false,
    "extraEu": false,
    "phase": "Prima Graduatoria Di Seconda Fase",
    "primary": 2,
    "secondary": 1,
    "isEnglish": true
  },
  "rankingSummary": {
    "courseSummarized": [
      {
        "averageBirthYear": 2004.36992,
        "averageEnglishCorrectAnswers": null,
        "averageOfWhoPassed": 78.6525,
        "averagePartialScores": {
          "Comprensione Verbale": 12.81220,
          "Fisica": 7.62098,
          "Matematica": 53.40707
        },
        "averageScoresOfAllStudents": 73.84024,
        "howManyCanEnroll": 36,
        "howManyOfa": {},
        "howManyStudents": 41,
        "location": "MILANO LEONARDO",
        "minScoreToEnroll": 49.28,
        "title": "INGEGNERIA CIVILE - CIVIL ENGINEERING"
      }
    ],
    "howManyCanEnroll": 36,
    "howManyStudents": 41,
    "resultsSummarized": {
      "30": 1,
      "33": 1,
      "42": 2,
      "48": 1,
      "49": 1,
      "50": 2,
      "55": 1,
      "59": 1,
      "65": 1,
      "72": 3,
      "73": 1,
      "77": 1,
      "79": 3,
      "81": 2,
      "83": 2,
      "85": 9,
      "86": 1,
      "88": 1,
      "90": 7
    }
  },
  "school": "Ingegneria",
  "url": {
    "pageEnum": 1,
    "url": "https://www.risultati-ammissione.polimi.it/2024_20056_34cf_html/2024_20056_generale.html"
  },
  "year": 2024
}